coreset/__init__.py
coreset/config.py
coreset/dataset/__init__.py
coreset/dataset/base.py
coreset/dataset/text_classification.py
coreset/lab/__init__.py
coreset/lab/experiments.py
coreset/metrics/__init__.py
coreset/metrics/base.py
coreset/metrics/coverage.py
coreset/metrics/distances.py
coreset/selection/__init__.py
coreset/selection/base.py
coreset/selection/random.py
coreset/utils/__init__.py
coreset/utils/device.py
coreset-0.0.1.dist-info/LICENSE
coreset-0.0.1.dist-info/METADATA
coreset-0.0.1.dist-info/WHEEL
coreset-0.0.1.dist-info/RECORD
