Metadata-Version: 2.3
Name: coreset
Version: 0.0.1
Summary: A flexible framework for experimenting with and evaluating different sample selection strategies
Author: Yasas Senarath
Requires-Python: >=3.9
Classifier: Programming Language :: Python :: 3
Classifier: Programming Language :: Python :: 3.9
Classifier: Programming Language :: Python :: 3.10
Classifier: Programming Language :: Python :: 3.11
Classifier: Programming Language :: Python :: 3.12
Classifier: Programming Language :: Python :: 3.13
Requires-Dist: datasets (>=2.15.0)
Requires-Dist: matplotlib (>=3.7.0)
Requires-Dist: nightjar (>=0.0.5,<0.0.6)
Requires-Dist: numpy (>=1.24.0)
Requires-Dist: pandas (>=2.1.0)
Requires-Dist: scikit-learn (>=1.3.0)
Requires-Dist: sentence-transformers (>=2.2.2)
Requires-Dist: torch (>=2.1.0)
Requires-Dist: tqdm (>=4.66.0)
Requires-Dist: transformers (>=4.36.0)
